LICENSE
MANIFEST.in
README.md
nutritionix.py
setup.py
nutritionix.egg-info/PKG-INFO
nutritionix.egg-info/SOURCES.txt
nutritionix.egg-info/dependency_links.txt
nutritionix.egg-info/not-zip-safe
nutritionix.egg-info/requires.txt
nutritionix.egg-info/top_level.txt