Metadata-Version: 1.0
Name: nutritionix
Version: 0.2
Summary: Nutritionix Python API wrapper
Home-page: https://github.com/leetrout/python-nutritionix/
Author: Lee Trout
Author-email: leetrout@gmail.com
License: UNKNOWN
Platform: UNKNOWN
Classifier: Development Status :: 4 - Beta
Classifier: Environment :: Web Environment
Classifier: Intended Audience :: Developers
Classifier: License :: OSI Approved :: MIT License
Classifier: Operating System :: OS Independent
Classifier: Programming Language :: Python
Classifier: Topic :: Internet :: WWW/HTTP
